setup.py
seleniumunclickable/__init__.py
seleniumunclickable/script.py
seleniumunclickable.egg-info/PKG-INFO
seleniumunclickable.egg-info/SOURCES.txt
seleniumunclickable.egg-info/dependency_links.txt
seleniumunclickable.egg-info/requires.txt
seleniumunclickable.egg-info/top_level.txt