Metadata-Version: 2.1
Name: seleniumunclickable
Version: 1.0.1
Summary: Generate QR Codes!
Home-page: https://github.com/yungestdev/seleniumunclickable
Author: yungestdev
Author-email: yungestdev@gmail.com
